netboxNinja/__init__.py
netboxNinja/__main__.py
netboxNinja/main.py
netboxNinja/netbox_ninja.py
netboxNinja/logic/__init__.py
netboxNinja/logic/csv_reader.py
netboxNinja/netbox_api/__init__.py
netboxNinja/netbox_api/device_manager.py
netboxNinja/netbox_api/interface_manager.py
netboxNinja/netbox_api/token_manager.py
netboxNinja/netbox_api/vlan_manager.py
netboxNinja-0.0.1.dist-info/LICENSE
netboxNinja-0.0.1.dist-info/METADATA
netboxNinja-0.0.1.dist-info/WHEEL
netboxNinja-0.0.1.dist-info/top_level.txt
netboxNinja-0.0.1.dist-info/RECORD
