Metadata-Version: 2.1
Name: netboxNinja
Version: 0.0.1
Summary: This tool is intended to insert data (for now interfaces) to Netbox via API.
Author: Timo Riedinger
Author-email: timo.riedinger@bechtle.com
License: MIT
Classifier: Programming Language :: Python :: 3.11
License-File: LICENSE
Requires-Dist: certifi ==2024.7.4
Requires-Dist: charset-normalizer ==3.3.2
Requires-Dist: click ==8.1.7
Requires-Dist: idna ==3.7
Requires-Dist: python-dotenv ==1.0.1
Requires-Dist: requests ==2.32.3
Requires-Dist: urllib3 ==2.2.2
